{
  "@context": {
  "schema": "http://example.org/schemas/",
  "tv": "schema:Tv",
  "radio": "schema:Radio",
  "generatedAt": {
    "@id": "http://www.w3.org/ns/prov#generatedAtTime",
    "@type": "http://www.w3.org/2001/XMLSchema#dateTime"
  },
  "name": {
    "@id": "schema:BroadcastService#name",
    "@type": "http://www.w3.org/2001/XMLSchema#string"
  }
},
  "@id": "http://example.org/bbc-services",
  "generatedAt": "2013-05-13T15:48:17.601Z",
  "@graph": [
{
  "@id": "http://www.bbc.co.uk/alba/",
  "@type": "tv",
  "name": "BBC Alba",
  "toll": "free",
  "languages": {
    "default": "gd-GB",
    "audio": ["gd-GB"],
    "subtitles": ["en-GB"]
  },
  "availability": [
    { "from": "17:00", "to": "00:00" }
  ],
  "logo": {

  },
  "url": {
    "home": "http://www.bbc.co.uk/alba/",
    "facebook": "https://www.facebook.com/BBCAlba",
    "twitter": "https://twitter.com/BellaBBCALBA"
  },
  "events": {
    "started": "2008-09-19T21:00:00.000Z",
    "ended": null
  }
}
,
{
  "@id": "http://www.bbc.co.uk/cymru",
  "@type": "tv",
  "name": "BBC Cymru",
  "toll": "free",
  "languages": {
    "default": "cy-GB",
    "audio": ["cy-GB"],
    "subtitles": ["en-GB"]
  },
  "availability": [],
  "logo": {

  },
  "url": {
    "home": "http://www.bbc.co.uk/cymru",
    "twitter": "https://twitter.com/bbccymru"
  },
  "events": {
    "started": "1964-02-09T00:00:00.000Z",
    "ended": null
  }
}
,
{
  "@id": "http://www.bbc.co.uk/bbcone",
  "@type": "tv",
  "name": "BBC One",
  "toll": "free",
  "languages": {
    "default": "en-GB",
    "audio": ["en-GB"],
    "subtitles": ["en-GB"]
  },
  "availability": [],
  "logo": {

  },
  "url": {
    "home": "http://www.bbc.co.uk/bbcone",
    "facebook": "https://www.facebook.com/BBCOne",
    "twitter": "https://twitter.com/bbcone"
  },
  "events": {
    "started": "1936-11-02T00:00:00.000Z",
    "ended": null
  }
}
,
{
  "@id": "http://www.bbc.co.uk/radio1",
  "@type": "radio",
  "name": "BBC Radio One",
  "toll": "free",
  "languages": {
    "default": "en-GB",
    "audio": ["en-GB"],
    "subtitles": ["en-GB"]
  },
  "availability": [],
  "logo": {

  },
  "url": {
    "home": "http://www.bbc.co.uk/radio1",
    "facebook": "https://www.facebook.com/bbcradio1‎",
    "twitter": "https://twitter.com/BBCR1‎"
  },
  "events": {
    "started": "1967-09-30T00:00:00.000Z",
    "ended": null
  }
}
,
{
  "@id": "http://www.bbc.co.uk/bbcthree",
  "@type": "tv",
  "name": "BBC Three",
  "toll": "free",
  "languages": {
    "default": "en-GB",
    "audio": ["en-GB"],
    "subtitles": ["en-GB"]
  },
  "availability": [
    { "from": "19:00", "to": "04:00" }
  ],
  "logo": {

  },
  "url": {
    "home": "http://www.bbc.co.uk/bbcthree",
    "facebook": "https://www.facebook.com/BBCThree",
    "twitter": "https://twitter.com/bbcthree"
  },
  "events": {
    "started": "2003-02-09T00:00:00.000Z",
    "ended": null
  }
}]}